allure_emailer/__init__.py
allure_emailer/cli.py
allure_emailer/config.py
allure_emailer/emailer.py
allure_emailer-0.1.2.dist-info/licenses/LICENSE
allure_emailer-0.1.2.dist-info/METADATA
allure_emailer-0.1.2.dist-info/WHEEL
allure_emailer-0.1.2.dist-info/entry_points.txt
allure_emailer-0.1.2.dist-info/top_level.txt
allure_emailer-0.1.2.dist-info/RECORD
