Metadata-Version: 2.4
Name: allure-emailer
Version: 0.1.2
Summary: CLI tool to send Allure test run summaries by email from CI pipelines
Author-email: Keinar <keinarelkayam@gmail.com>
License: MIT
Keywords: allure,email,ci
Requires-Python: >=3.7
License-File: LICENSE
Requires-Dist: typer>=0.9.0
Requires-Dist: python-dotenv>=1.0.0
Requires-Dist: requests>=2.25.0
Dynamic: license-file
